<?xml version="1.0" encoding="UTF-8"?>
<beans
  xmlns="http://www.springframework.org/schema/beans"
  xmlns:xsi="http://www.w3.org/2001/XMLSchema-instance"
  xmlns:context="http://www.springframework.org/schema/context"
  xmlns:mvc="http://www.springframework.org/schema/mvc"
  xsi:schemaLocation="http://www.springframework.org/schema/mvc
                      http://www.springframework.org/schema/mvc/spring-mvc.xsd
                      http://www.springframework.org/schema/beans
                      http://www.springframework.org/schema/beans/spring-beans.xsd
                      http://www.springframework.org/schema/context
                      http://www.springframework.org/schema/context/spring-context.xsd">

  <bean id="properties" class="org.springframework.context.support.PropertySourcesPlaceholderConfigurer">
    <property name="locations">
      <list>
        <value>classpath:crypt.properties</value>
        <value>classpath:jdbc.properties</value>
        <value>classpath:system.properties</value>
        <value>classpath:aws.properties</value>
        <value>classpath:healthInfo.properties</value>
      </list>
    </property>
  </bean>
  <!-- healthinfo.properties -->
  <bean id="healthInfoProperties" class="jp.co.ha.business.io.file.properties.HealthInfoProperties" lazy-init="true">
    <property name="referenceFilePath" value="${referenceFilePath}" />
    <property name="healthInfoRegistBatchFilePath" value="${healthInfoRegistBatchFilePath}" />
  </bean>
  <!-- aws.properties -->
  <bean id="awsConfig" class="jp.co.ha.business.aws.AwsConfig" lazy-init="true">
    <property name="accesskey" value="${aws.accesskey}" />
    <property name="secretAccesskey" value="${aws.secret.accesskey}" />
    <property name="region" value="${aws.region}" />
  </bean>
  <!-- CRUD -->
  <context:component-scan base-package="jp.co.ha.business.db.crud.read.impl" />
  <context:component-scan base-package="jp.co.ha.business.db.crud.create.impl" />
  <context:component-scan base-package="jp.co.ha.business.db.crud.update.impl" />
  <context:component-scan base-package="jp.co.ha.business.db.crud.delete.impl" />

  <!-- API -->
  <context:component-scan base-package="jp.co.ha.business.api" />

  <!-- Business -->
  <context:component-scan base-package="jp.co.ha.business.healthInfo.*.impl" />

  <!-- AWS -->
  <context:component-scan base-package="jp.co.ha.business.aws" />
</beans>